secure_proxy/__init__.py
secure_proxy/client.py
secure_proxy-0.8.0.dist-info/METADATA
secure_proxy-0.8.0.dist-info/WHEEL
secure_proxy-0.8.0.dist-info/top_level.txt
secure_proxy-0.8.0.dist-info/RECORD
