Metadata-Version: 2.4
Name: secure_proxy
Version: 0.8.0
Summary: Proxy orqali so‘rov yuborish uchun kutubxona
Home-page: https://github.com/abduvohid26/secure_proxy
Author: Abduvohid
Author-email: abdujalilov2629@gmail.com
Classifier: Programming Language :: Python :: 3
Classifier: License :: OSI Approved :: MIT License
Classifier: Operating System :: OS Independent
Requires-Python: >=3.6
Requires-Dist: httpx
Dynamic: author
Dynamic: author-email
Dynamic: classifier
Dynamic: description
Dynamic: description-content-type
Dynamic: home-page
Dynamic: requires-dist
Dynamic: requires-python
Dynamic: summary
